rtea-0.3.4.dist-info/METADATA
rtea-0.3.4.dist-info/WHEEL
rtea-0.3.4.dist-info/license_files/LICENSE
rtea/py.typed
rtea/_pytea.py
rtea/__init__.pyi
rtea/__init__.py
rtea/_pytea.pyi
rtea/rtea.abi3.so
rtea-0.3.4.dist-info/RECORD
