Metadata-Version: 2.1
Name: rtea
Version: 0.3.4
Classifier: Development Status :: 5 - Production/Stable
Classifier: Intended Audience :: Developers
Classifier: License :: OSI Approved :: MIT License
Classifier: Operating System :: MacOS
Classifier: Operating System :: Microsoft :: Windows
Classifier: Operating System :: POSIX :: Linux
Classifier: Programming Language :: Python :: 3
Classifier: Programming Language :: Python :: 3.7
Classifier: Programming Language :: Python :: 3.8
Classifier: Programming Language :: Python :: 3.9
Classifier: Programming Language :: Python :: 3.10
Classifier: Programming Language :: Python
Classifier: Programming Language :: Rust
Classifier: Typing :: Typed
License-File: LICENSE
Summary: Bring fast TEA cipher to Python. Powered by Rust.
Home-Page: https://github.com/zkonge/rtea
Author: zkonge <zkonge@outlook.com>
Author-email: zkonge <zkonge@outlook.com>
Requires-Python: >=3.7
Project-URL: Source Code, https://github.com/zkonge/rtea
